AUTHORS.rst
CHANGELOG.rst
LICENSE
MANIFEST.in
README.rst
setup.py
jmbo_social.egg-info/PKG-INFO
jmbo_social.egg-info/SOURCES.txt
jmbo_social.egg-info/dependency_links.txt
jmbo_social.egg-info/not-zip-safe
jmbo_social.egg-info/requires.txt
jmbo_social.egg-info/top_level.txt
social/__init__.py
social/backends.py
social/class_modifiers.py
social/constants.py
social/models.py
social/tests.py
social/urls.py
social/utils.py
social/views.py
social/media/social/images/facebook_landscape.png
social/media/social/images/facebook_square.png
social/media/social/images/twitter_landscape.png
social/media/social/images/twitter_square.png
social/templates/social/invitation_confirm_done.html
social/templates/social/inclusion_tags/facebook_connect_button.html
social/templates/social/inclusion_tags/facebook_connect_form.html
social/templates/social/inclusion_tags/facebook_invite_friends.html
social/templates/social/inclusion_tags/friendship_setup_button.html
social/templates/social/inclusion_tags/friendship_setup_button_include.html
social/templates/social/inclusion_tags/twitter_connect_button.html
social/templates/social/inclusion_tags/twitter_connect_form.html
social/templatetags/__init__.py
social/templatetags/social_inclusion_tags.py
social/templatetags/social_template_tags.py