Metadata-Version: 1.0
Name: jmbo-social
Version: 0.0.6
Summary: Jmbo social app collecting 3rd party social apps.
Home-page: http://github.com/praekelt/jmbo-social
Author: Praekelt Foundation
Author-email: dev@praekelt.com
License: BSD
Platform: UNKNOWN
Classifier: Programming Language :: Python
Classifier: License :: OSI Approved :: BSD License
Classifier: Development Status :: 4 - Beta
Classifier: Operating System :: OS Independent
Classifier: Framework :: Django
Classifier: Intended Audience :: Developers
Classifier: Topic :: Internet :: WWW/HTTP :: Dynamic Content
